{
  "type": "TABLE",
  "title": "Բ.6.5. Կանխիկ դրամ",
  "value": {
    "headerItems": [
      {
        "name": "NN ը/կ",
        "isNumbering": true,
        "colSpan": 1
      },
      {
        "name": "Սեփականատիրոջ անունը, ազգանունը, հայրանունը",
        "isNumbering": false,
        "colSpan": 1
      },
      {
        "name": "Պաշտոնի ստանձնման կամ դադարեցման օրվա դրությամբ առկա կանխիկ դրամի գումարը և արժույթը",
        "isNumbering": false,
        "colSpan": 1
      },
      {
        "name": "Պաշտոնի ստանձնման կամ դադարեցման օրվա դրությամբ առկա կանխիկ դրամի ծագման աղբյուրը",
        "isNumbering": false,
        "colSpan": 1
      }
    ],
    "rows": [
      ["1.", "ՌԱԶՄԻԿ ԳԱՍՊԱՐՅԱՆ ԱՐԹՈՒՐԻ", "$ 7,000", "Պաշտպանված"],
      ["2.", "ՌԱԶՄԻԿ ԳԱՍՊԱՐՅԱՆ ԱՐԹՈՒՐԻ", "֏ 2,000,000", "Պաշտպանված"]
    ],
    "footerItems": []
  },
  "properties": {
    "type": "TABLE",
    "xs": 12,
    "s": 12,
    "m": 12
  }
}
